aind_smartsheet_api/__init__.py
aind_smartsheet_api/client.py
aind_smartsheet_api/models.py
aind_smartsheet_api-0.2.1.dist-info/LICENSE
aind_smartsheet_api-0.2.1.dist-info/METADATA
aind_smartsheet_api-0.2.1.dist-info/WHEEL
aind_smartsheet_api-0.2.1.dist-info/top_level.txt
aind_smartsheet_api-0.2.1.dist-info/RECORD
