Metadata-Version: 2.1
Name: aind-smartsheet-api
Version: 0.2.1
Summary: Helps to convert Smartsheet json into Pydantic models
Author: Allen Institute for Neural Dynamics
License: MIT
Classifier: Programming Language :: Python :: 3
Requires-Python: >=3.8
License-File: LICENSE
Requires-Dist: smartsheet-python-sdk >=3.0
Requires-Dist: pydantic-settings >=2.0
Requires-Dist: pydantic >=2.0
Provides-Extra: dev
Requires-Dist: black ; extra == 'dev'
Requires-Dist: coverage ; extra == 'dev'
Requires-Dist: flake8 ; extra == 'dev'
Requires-Dist: interrogate ; extra == 'dev'
Requires-Dist: isort ; extra == 'dev'
Requires-Dist: Sphinx ; extra == 'dev'
Requires-Dist: furo ; extra == 'dev'
